discord_trad_bot/__init__.py
discord_trad_bot/constants.py
discord_trad_bot/db.py
discord_trad_bot/main.py
discord_trad_bot/utils.py
discord_trad_bot/commands/__init__.py
discord_trad_bot/commands/admin_commands.py
discord_trad_bot/commands/misc_commands.py
discord_trad_bot/commands/user_commands.py
discord_trad_bot/tests/__init__.py
discord_trad_bot/tests/test_utils.py
discord_trad_bot-2.0.0.dist-info/METADATA
discord_trad_bot-2.0.0.dist-info/WHEEL
discord_trad_bot-2.0.0.dist-info/entry_points.txt
discord_trad_bot-2.0.0.dist-info/RECORD
