Metadata-Version: 2.4
Name: discord-trad-bot
Version: 2.0.0
Summary: A Discord bot that automatically translates messages in specified channels
Author-email: Pierre Tsia <pierre.tsiakkaros@gmail.com>
License-Expression: MIT
Requires-Python: >=3.8
Requires-Dist: aiosqlite==0.19.0
Requires-Dist: discord-py==2.3.2
Requires-Dist: googletrans==4.0.0-rc1
Requires-Dist: python-dotenv==1.0.0
Requires-Dist: sqlalchemy==2.0.23
